densityx/__init__.py
densityx-1.2.0.dist-info/LICENSE
densityx-1.2.0.dist-info/METADATA
densityx-1.2.0.dist-info/WHEEL
densityx-1.2.0.dist-info/top_level.txt
densityx-1.2.0.dist-info/RECORD
